{
  "id": "15642520",
  "lines": [
    {
      "400": "      PrintSetupRecord rec = new PrintSetupRecord();\n",
      "401": "      rec.field_1_paper_size = field_1_paper_size;\n",
      "402": "      rec.field_2_scale = field_2_scale;\n",
      "403": "      rec.field_3_page_start = field_3_page_start;\n",
      "404": "      rec.field_4_fit_width = field_4_fit_width;\n",
      "405": "      rec.field_5_fit_height = field_5_fit_height;\n",
      "406": "      rec.field_6_options = field_6_options;\n",
      "407": "      rec.field_7_hresolution = field_7_hresolution;\n",
      "408": "      rec.field_8_vresolution = field_8_vresolution;\n",
      "409": "      rec.field_9_headermargin = field_9_headermargin;\n",
      "410": "      rec.field_10_footermargin = field_10_footermargin;\n",
      "411": "      rec.field_11_copies = field_11_copies;\n"
    }
  ]
}