{
  "id": "15642358",
  "lines": [
    {
      "665": "        ExtendedFormatRecord retval =\n"
    },
    {
      "679": "        ExtendedFormatRecord xf = createExtendedFormat();\n"
    },
    {
      "1287": "        ExtendedFormatRecord retval = new ExtendedFormatRecord();\n",
      "1292": "                retval.setFontIndex(( short ) 0);\n",
      "1293": "                retval.setFormatIndex(( short ) 0);\n",
      "1294": "                retval.setCellOptions(( short ) 0xfffffff5);\n",
      "1295": "                retval.setAlignmentOptions(( short ) 0x20);\n",
      "1296": "                retval.setIndentionOptions(( short ) 0);\n",
      "1297": "                retval.setBorderOptions(( short ) 0);\n",
      "1298": "                retval.setPaletteOptions(( short ) 0);\n",
      "1299": "                retval.setAdtlPaletteOptions(( short ) 0);\n",
      "1300": "                retval.setFillPaletteOptions(( short ) 0x20c0);\n",
      "1304": "                retval.setFontIndex(( short ) 1);\n",
      "1308": "                retval.setIndentionOptions(( short ) 0xfffff400);\n",
      "1328": "                retval.setFontIndex(( short ) 2);\n",
      "1475": "                retval.setCellOptions(( short ) 0x1);\n",
      "1477": "                retval.setIndentionOptions(( short ) 0x0);\n",
      "1487": "                retval.setFormatIndex(( short ) 0x2b);\n",
      "1490": "                retval.setIndentionOptions(( short ) 0xfffff800);\n",
      "1499": "                retval.setFormatIndex(( short ) 0x29);\n",
      "1511": "                retval.setFormatIndex(( short ) 0x2c);\n",
      "1523": "                retval.setFormatIndex(( short ) 0x2a);\n",
      "1535": "                retval.setFormatIndex(( short ) 0x9);\n",
      "1547": "                retval.setFontIndex(( short ) 5);\n",
      "1548": "                retval.setFormatIndex(( short ) 0x0);\n",
      "1551": "                retval.setIndentionOptions(( short ) 0x800);\n",
      "1559": "                retval.setFontIndex(( short ) 6);\n",
      "1563": "                retval.setIndentionOptions(( short ) 0x5c00);\n",
      "1572": "                retval.setFormatIndex(( short ) 0x31);\n",
      "1584": "                retval.setFormatIndex(( short ) 0x8);\n"
    },
    {
      "1615": "        ExtendedFormatRecord retval = new ExtendedFormatRecord();\n",
      "1617": "        retval.setFontIndex(( short ) 0);\n",
      "1618": "        retval.setFormatIndex(( short ) 0x0);\n",
      "1619": "        retval.setCellOptions(( short ) 0x1);\n",
      "1620": "        retval.setAlignmentOptions(( short ) 0x20);\n",
      "1621": "        retval.setIndentionOptions(( short ) 0);\n",
      "1622": "        retval.setBorderOptions(( short ) 0);\n",
      "1623": "        retval.setPaletteOptions(( short ) 0);\n",
      "1624": "        retval.setAdtlPaletteOptions(( short ) 0);\n",
      "1625": "        retval.setFillPaletteOptions(( short ) 0x20c0);\n",
      "1626": "        retval.setTopBorderPaletteIdx(HSSFColor.BLACK.index);\n",
      "1627": "        retval.setBottomBorderPaletteIdx(HSSFColor.BLACK.index);\n",
      "1628": "        retval.setLeftBorderPaletteIdx(HSSFColor.BLACK.index);\n",
      "1629": "        retval.setRightBorderPaletteIdx(HSSFColor.BLACK.index);\n"
    }
  ]
}